pypaystack2/__init__.py
pypaystack2/_metadata.py
pypaystack2/base_clients.py
pypaystack2/cli.py
pypaystack2/enums.py
pypaystack2/exceptions.py
pypaystack2/fees_calculation_mixin.py
pypaystack2/main_clients.py
pypaystack2/models/__init__.py
pypaystack2/models/payload_models.py
pypaystack2/models/response_models.py
pypaystack2/py.typed
pypaystack2/sub_clients/__init__.py
pypaystack2/sub_clients/async_clients/__init__.py
pypaystack2/sub_clients/async_clients/apple_pay.py
pypaystack2/sub_clients/async_clients/bulk_charges.py
pypaystack2/sub_clients/async_clients/charge.py
pypaystack2/sub_clients/async_clients/customers.py
pypaystack2/sub_clients/async_clients/dedicated_accounts.py
pypaystack2/sub_clients/async_clients/disputes.py
pypaystack2/sub_clients/async_clients/integration.py
pypaystack2/sub_clients/async_clients/miscellaneous.py
pypaystack2/sub_clients/async_clients/payment_pages.py
pypaystack2/sub_clients/async_clients/payment_requests.py
pypaystack2/sub_clients/async_clients/plans.py
pypaystack2/sub_clients/async_clients/products.py
pypaystack2/sub_clients/async_clients/refunds.py
pypaystack2/sub_clients/async_clients/settlements.py
pypaystack2/sub_clients/async_clients/splits.py
pypaystack2/sub_clients/async_clients/subaccounts.py
pypaystack2/sub_clients/async_clients/subscriptions.py
pypaystack2/sub_clients/async_clients/terminals.py
pypaystack2/sub_clients/async_clients/transactions.py
pypaystack2/sub_clients/async_clients/transfer_recipients.py
pypaystack2/sub_clients/async_clients/transfers.py
pypaystack2/sub_clients/async_clients/transfers_control.py
pypaystack2/sub_clients/async_clients/verification.py
pypaystack2/sub_clients/sync_clients/__init__.py
pypaystack2/sub_clients/sync_clients/apple_pay.py
pypaystack2/sub_clients/sync_clients/bulk_charges.py
pypaystack2/sub_clients/sync_clients/charge.py
pypaystack2/sub_clients/sync_clients/customers.py
pypaystack2/sub_clients/sync_clients/dedicated_accounts.py
pypaystack2/sub_clients/sync_clients/disputes.py
pypaystack2-3.1.0.dist-info/WHEEL
pypaystack2-3.1.0.dist-info/entry_points.txt
pypaystack2-3.1.0.dist-info/METADATA
pypaystack2-3.1.0.dist-info/RECORD
