Metadata-Version: 2.4
Name: pypaystack2
Version: 3.1.0
Summary: A developer-friendly client library for Paystack
Keywords: paystack-python,pypaystack,paystack,paystackapi
Author: Gbenga Adeyi
Author-email: Gbenga Adeyi <adeyigbenga005@gmail.com>
License-Expression: MIT
Classifier: License :: OSI Approved :: MIT License
Classifier: Programming Language :: Python
Classifier: Programming Language :: Python :: 3
Requires-Dist: httpx>=0.28.1
Requires-Dist: pydantic>=2.12.5
Requires-Dist: fastapi[standard]>=0.123.10 ; extra == 'webhook'
Requires-Dist: ngrok>=1.4.0 ; extra == 'webhook'
Requires-Dist: python-dotenv>=1.2.1 ; extra == 'webhook'
Requires-Dist: typer-slim[standard]>=0.20.0 ; extra == 'webhook'
Requires-Python: >=3.11
Provides-Extra: webhook
